{"nodes": [{"id": "tests_test_pin_it_js", "label": "test-pin-it.js", "file_type": "code", "source_file": "tests\\test-pin-it.js", "source_location": "L1"}], "edges": [{"source": "tests_test_pin_it_js", "target": "tests_test_runner_ts", "relation": "imports_from", "confidence": "EXTRACTED", "source_file": "tests\\test-pin-it.js", "source_location": "L1", "weight": 1.0}, {"source": "tests_test_pin_it_js", "target": "js_pin_it_ts", "relation": "imports_from", "confidence": "EXTRACTED", "source_file": "tests\\test-pin-it.js", "source_location": "L2", "weight": 1.0}], "raw_calls": []}