{"nodes": [{"id": "js_region_ranger_js", "label": "region-ranger.js", "file_type": "code", "source_file": "js\\region-ranger.js", "source_location": "L1"}, {"id": "region_ranger_pickquestions", "label": "pickQuestions()", "file_type": "code", "source_file": "js\\region-ranger.js", "source_location": "L18"}, {"id": "region_ranger_checkanswer", "label": "checkAnswer()", "file_type": "code", "source_file": "js\\region-ranger.js", "source_location": "L22"}, {"id": "region_ranger_shouldshowlegend", "label": "shouldShowLegend()", "file_type": "code", "source_file": "js\\region-ranger.js", "source_location": "L27"}, {"id": "region_ranger_mountregionranger", "label": "mountRegionRanger()", "file_type": "code", "source_file": "js\\region-ranger.js", "source_location": "L31"}, {"id": "region_ranger_updatetimer", "label": "updateTimer()", "file_type": "code", "source_file": "js\\region-ranger.js", "source_location": "L156"}, {"id": "region_ranger_shuffle", "label": "shuffle()", "file_type": "code", "source_file": "js\\region-ranger.js", "source_location": "L168"}, {"id": "region_ranger_escapehtml", "label": "escapeHtml()", "file_type": "code", "source_file": "js\\region-ranger.js", "source_location": "L177"}], "edges": [{"source": "js_region_ranger_js", "target": "js_scoring_ts", "relation": "imports_from", "confidence": "EXTRACTED", "source_file": "js\\region-ranger.js", "source_location": "L1", "weight": 1.0}, {"source": "js_region_ranger_js", "target": "region_ranger_pickquestions", "relation": "contains", "confidence": "EXTRACTED", "source_file": "js\\region-ranger.js", "source_location": "L18", "weight": 1.0}, {"source": "js_region_ranger_js", "target": "region_ranger_checkanswer", "relation": "contains", "confidence": "EXTRACTED", "source_file": "js\\region-ranger.js", "source_location": "L22", "weight": 1.0}, {"source": "js_region_ranger_js", "target": "region_ranger_shouldshowlegend", "relation": "contains", "confidence": "EXTRACTED", "source_file": "js\\region-ranger.js", "source_location": "L27", "weight": 1.0}, {"source": "js_region_ranger_js", "target": "region_ranger_mountregionranger", "relation": "contains", "confidence": "EXTRACTED", "source_file": "js\\region-ranger.js", "source_location": "L31", "weight": 1.0}, {"source": "js_region_ranger_js", "target": "region_ranger_updatetimer", "relation": "contains", "confidence": "EXTRACTED", "source_file": "js\\region-ranger.js", "source_location": "L156", "weight": 1.0}, {"source": "js_region_ranger_js", "target": "region_ranger_shuffle", "relation": "contains", "confidence": "EXTRACTED", "source_file": "js\\region-ranger.js", "source_location": "L168", "weight": 1.0}, {"source": "js_region_ranger_js", "target": "region_ranger_escapehtml", "relation": "contains", "confidence": "EXTRACTED", "source_file": "js\\region-ranger.js", "source_location": "L177", "weight": 1.0}, {"source": "region_ranger_pickquestions", "target": "region_ranger_shuffle", "relation": "calls", "confidence": "EXTRACTED", "source_file": "js\\region-ranger.js", "source_location": "L19", "weight": 1.0}, {"source": "region_ranger_mountregionranger", "target": "region_ranger_pickquestions", "relation": "calls", "confidence": "EXTRACTED", "source_file": "js\\region-ranger.js", "source_location": "L33", "weight": 1.0}], "raw_calls": [{"caller_nid": "region_ranger_pickquestions", "callee": "slice", "source_file": "js\\region-ranger.js", "source_location": "L19"}, {"caller_nid": "region_ranger_checkanswer", "callee": "find", "source_file": "js\\region-ranger.js", "source_location": "L23"}, {"caller_nid": "region_ranger_checkanswer", "callee": "Boolean", "source_file": "js\\region-ranger.js", "source_location": "L24"}, {"caller_nid": "region_ranger_mountregionranger", "callee": "then", "source_file": "js\\region-ranger.js", "source_location": "L32"}, {"caller_nid": "region_ranger_mountregionranger", "callee": "fetch", "source_file": "js\\region-ranger.js", "source_location": "L32"}, {"caller_nid": "region_ranger_mountregionranger", "callee": "renderQuestion", "source_file": "js\\region-ranger.js", "source_location": "L153"}, {"caller_nid": "region_ranger_updatetimer", "callee": "getElementById", "source_file": "js\\region-ranger.js", "source_location": "L157"}, {"caller_nid": "region_ranger_updatetimer", "callee": "max", "source_file": "js\\region-ranger.js", "source_location": "L159"}, {"caller_nid": "region_ranger_shuffle", "callee": "floor", "source_file": "js\\region-ranger.js", "source_location": "L171"}, {"caller_nid": "region_ranger_shuffle", "callee": "random", "source_file": "js\\region-ranger.js", "source_location": "L171"}, {"caller_nid": "region_ranger_escapehtml", "callee": "replaceAll", "source_file": "js\\region-ranger.js", "source_location": "L178"}, {"caller_nid": "region_ranger_escapehtml", "callee": "replaceAll", "source_file": "js\\region-ranger.js", "source_location": "L178"}, {"caller_nid": "region_ranger_escapehtml", "callee": "replaceAll", "source_file": "js\\region-ranger.js", "source_location": "L178"}, {"caller_nid": "region_ranger_escapehtml", "callee": "replaceAll", "source_file": "js\\region-ranger.js", "source_location": "L178"}, {"caller_nid": "region_ranger_escapehtml", "callee": "replaceAll", "source_file": "js\\region-ranger.js", "source_location": "L178"}, {"caller_nid": "region_ranger_escapehtml", "callee": "String", "source_file": "js\\region-ranger.js", "source_location": "L178"}]}